dialogs/__init__.py
dialogs/about.py
dialogs/helpers.py
dialogs/ui_options.py
hivedesktop/__init__.py
hivedesktop/fix_qt_import_error.py
hivedesktop/helpers.py
hivedesktop/hivedesktop_rc.py
hivedesktop/main.py
hivedesktop/mdrenderer.py
hivedesktop/mdx_url.py
hivedesktop/mdx_video.py
hivedesktop/store_account_history.py
hivedesktop/ui_mainwindow.py
hivedesktop/dialogs/__init__.py
hivedesktop/dialogs/about.py
hivedesktop/dialogs/helpers.py
hivedesktop/dialogs/options.py
hivedesktop/dialogs/ui_options.py
hivedesktop/threads/__init__.py
hivedesktop/threads/markdown.py
hivedesktop/threads/thread.py
hivedesktop/widgets/__init__.py
hivedesktop/widgets/webview.py
hivedesktop-0.3.3.data/data/LICENSE
threads/__init__.py
threads/account_feed.py
threads/markdown.py
threads/thread.py
hivedesktop-0.3.3.dist-info/LICENSE
hivedesktop-0.3.3.dist-info/METADATA
hivedesktop-0.3.3.dist-info/WHEEL
hivedesktop-0.3.3.dist-info/entry_points.txt
hivedesktop-0.3.3.dist-info/top_level.txt
hivedesktop-0.3.3.dist-info/RECORD
