Metadata-Version: 2.1
Name: hivedesktop
Version: 0.3.3
Summary: Fetches your Amazon order history and matching/tags your Mint transactions
Home-page: https://github.com/holgern/hivedesktop
Author: holger80
Author-email: holgernahrstaedt@gmx.de
License: GPLv3
Keywords: hive blockchain pyqt desktop app
Platform: UNKNOWN
Classifier: Programming Language :: Python :: 3
Classifier: License :: OSI Approved :: GNU General Public License v3 (GPLv3)
Classifier: Operating System :: OS Independent
Classifier: Topic :: Office/Business :: Financial
Requires-Python: >=3
Requires-Dist: PyQt5 (==5.14.2)
Requires-Dist: PyQtWebEngine (==5.14)
Requires-Dist: markdown
Requires-Dist: Pygments
Requires-Dist: mdx-smartypants
Requires-Dist: dataset
Requires-Dist: deepdish
Requires-Dist: jinja2
Requires-Dist: markupsafe
Requires-Dist: pymdown-extensions
Requires-Dist: beem
Requires-Dist: cryptography
Requires-Dist: pycryptodome
Requires-Dist: python-dateutil
